target_elasticsearch/__init__.py
target_elasticsearch/sinks.py
target_elasticsearch/target.py
target_elasticsearch-2.0.2.dist-info/METADATA
target_elasticsearch-2.0.2.dist-info/WHEEL
target_elasticsearch-2.0.2.dist-info/entry_points.txt
target_elasticsearch-2.0.2.dist-info/licenses/LICENSE
target_elasticsearch-2.0.2.dist-info/RECORD
