Metadata-Version: 2.4
Name: target-elasticsearch
Version: 2.0.2
Summary: `target-elasticsearch` is a singer target using the meltano SDK for targets
Author-email: DT Mirizzi <dtmirizzi@gmail.com>
License-Expression: GPL-3.0
License-File: LICENSE
Keywords: ELT,elasticsearch,meltano,singer,target
Requires-Python: <3.13,>=3.9.1
Requires-Dist: elasticsearch<9,>=8.14.0
Requires-Dist: jinja2>=3.1.2
Requires-Dist: jsonpath-ng>=1.5.3
Requires-Dist: requests>=2.25.1
Requires-Dist: singer-sdk>=0.38.0
Requires-Dist: time-machine>=2.8.2
Requires-Dist: types-python-dateutil>=2.8.19
Requires-Dist: typing-extensions>=4.4.0
